adcc_backup/__init__.py
adcc_backup/config.py
adcc_backup/client/__init__.py
adcc_backup/client/eth_event.py
adcc_backup/client/rsync.py
adcc_backup/scripts/__init__.py
adcc_backup/scripts/adcc_backup_client.py
adcc_backup/scripts/adcc_backup_server.py
adcc_backup/scripts/adcc_backup_utils.py
adcc_backup/server/__init__.py
adcc_backup/server/fixer.py
adcc_backup-1.0.3.dist-info/LICENSE
adcc_backup-1.0.3.dist-info/METADATA
adcc_backup-1.0.3.dist-info/WHEEL
adcc_backup-1.0.3.dist-info/entry_points.txt
adcc_backup-1.0.3.dist-info/top_level.txt
adcc_backup-1.0.3.dist-info/RECORD
