Metadata-Version: 2.1
Name: adcc-backup
Version: 1.0.3
Summary: Upload data
Home-page: https://gitlabee.dt.renault.com/ADCC/server_backup/-/tree/develop
Author: Marco Treglia
License: MIT License
Requires-Dist: markipy
